conkeyscan/__init__.py
conkeyscan/conkeyscan.py
conkeyscan/config/__init__.py
conkeyscan/config/dict.txt
conkeyscan-1.1.0.dist-info/LICENSE
conkeyscan-1.1.0.dist-info/METADATA
conkeyscan-1.1.0.dist-info/WHEEL
conkeyscan-1.1.0.dist-info/entry_points.txt
conkeyscan-1.1.0.dist-info/top_level.txt
conkeyscan-1.1.0.dist-info/RECORD
