Metadata-Version: 2.1
Name: conkeyscan
Version: 1.1.0
Summary: A Pentesters Confluence Keyword Scanner
Home-page: https://github.com/CompassSecurity/conkeyscan
Author: Jan Friedli
License: mit
License-File: LICENSE
Requires-Dist: loguru
Requires-Dist: atlassian-python-api>=3
Requires-Dist: beautifulsoup4>=4
Requires-Dist: requests-ratelimiter
Requires-Dist: clize>=5
Requires-Dist: random-user-agent>=1
Requires-Dist: readchar
Requires-Dist: PySocks>=1
